polls/__init__.py
polls/admin.py
polls/apps.py
polls/models.py
polls/tests.py
polls/urls.py
polls/views.py
polls/migrations/0001_initial.py
polls/migrations/0002_auto_20190830_0657.py
polls/migrations/0002_auto_20190830_0657_squashed_0003_auto_20190830_0658.py
polls/migrations/0003_auto_20190830_0658.py
polls/migrations/__init__.py
polls/static/polls/style.css
polls/templates/admin/base_site.html
polls/templates/polls/base.html
polls/templates/polls/detail_question.html
polls/templates/polls/index.html
polls/templates/polls/question_list.html
polls/templates/polls/result.html
django_huyho_polls-0.1.dist-info/LICENCE
django_huyho_polls-0.1.dist-info/METADATA
django_huyho_polls-0.1.dist-info/WHEEL
django_huyho_polls-0.1.dist-info/top_level.txt
django_huyho_polls-0.1.dist-info/RECORD
